README.md
setup.py
src/selenium_super/__init__.py
src/selenium_super/actions.py
src/selenium_super/auth.py
src/selenium_super/driver_helpers.py
src/selenium_super/enums.py
src/selenium_super/file_utils.py
src/selenium_super/folder_utils.py
src/selenium_super/helpers.py
src/selenium_super/js.py
src/selenium_super/localstorage.py
src/selenium_super/nordvpn.py
src/selenium_super/process_multi_tasks.py
src/selenium_super/selenium_super.py
src/selenium_super/telegram_api.py
src/selenium_super/telethon_helpers.py
src/selenium_super/time_utils.py
src/selenium_super.egg-info/PKG-INFO
src/selenium_super.egg-info/SOURCES.txt
src/selenium_super.egg-info/dependency_links.txt
src/selenium_super.egg-info/requirements.txt
src/selenium_super.egg-info/requires.txt
src/selenium_super.egg-info/top_level.txt